README.md
setup.py
FlowMaster.egg-info/PKG-INFO
FlowMaster.egg-info/SOURCES.txt
FlowMaster.egg-info/dependency_links.txt
FlowMaster.egg-info/entry_points.txt
FlowMaster.egg-info/requires.txt
FlowMaster.egg-info/top_level.txt
flowmaster/__init__.py
flowmaster/__main__.py
flowmaster/database.py
flowmaster/dataschema.py
flowmaster/enums.py
flowmaster/exceptions.py
flowmaster/flow.py
flowmaster/models.py
flowmaster/notebook.py
flowmaster/pool.py
flowmaster/service.py
flowmaster/setttings.py
flowmaster/cli/__init__.py
flowmaster/cli/db.py
flowmaster/cli/item.py
flowmaster/cli/notebook.py
flowmaster/executors/__init__.py
flowmaster/executors/exceptions.py
flowmaster/operators/__init__.py
flowmaster/operators/base/__init__.py
flowmaster/operators/base/core.py
flowmaster/operators/base/policy.py
flowmaster/operators/base/work.py
flowmaster/operators/etl/__init__.py
flowmaster/operators/etl/core.py
flowmaster/operators/etl/dataschema.py
flowmaster/operators/etl/enums.py
flowmaster/operators/etl/policy.py
flowmaster/operators/etl/work.py
flowmaster/operators/etl/loaders/__init__.py
flowmaster/operators/etl/loaders/clickhouse/__init__.py
flowmaster/operators/etl/loaders/clickhouse/policy.py
flowmaster/operators/etl/loaders/clickhouse/service.py
flowmaster/operators/etl/loaders/csv/__init__.py
flowmaster/operators/etl/loaders/csv/policy.py
flowmaster/operators/etl/loaders/csv/service.py
flowmaster/operators/etl/providers/__init__.py
flowmaster/operators/etl/providers/abstract.py
flowmaster/operators/etl/providers/criteo/__init__.py
flowmaster/operators/etl/providers/criteo/export.py
flowmaster/operators/etl/providers/criteo/policy.py
flowmaster/operators/etl/providers/criteo/transform.py
flowmaster/operators/etl/providers/csv/__init__.py
flowmaster/operators/etl/providers/csv/export.py
flowmaster/operators/etl/providers/csv/policy.py
flowmaster/operators/etl/providers/fakedata/__init__.py
flowmaster/operators/etl/providers/fakedata/export.py
flowmaster/operators/etl/providers/fakedata/policy.py
flowmaster/operators/etl/providers/flowmaster_data/__init__.py
flowmaster/operators/etl/providers/flowmaster_data/export.py
flowmaster/operators/etl/providers/flowmaster_data/policy.py
