Metadata-Version: 2.1
Name: FlowMaster
Version: 0.7.1
Summary: ETL flow framework based on Yaml configs in Python
Home-page: https://github.com/pavelmaksimov/flowmaster
Author: Pavel Maksimov
Author-email: vur21@ya.ru
License: GPLv3
Keywords: etl,flowmaster,flow,airflow,prefect,schedule,scheduler,tasker
Platform: UNKNOWN
Requires-Python: >=3.9
Provides-Extra: clickhouse
Provides-Extra: postgres
Provides-Extra: mysql
Provides-Extra: yandexmetrika
Provides-Extra: yandexdirect
Provides-Extra: criteo
Provides-Extra: googlesheets
Provides-Extra: webui
